graphqt/__init__.py
graphqt/graphqt.py
graphqt-0.2.data/scripts/graphqt.py
graphqt-0.2.dist-info/DESCRIPTION.rst
graphqt-0.2.dist-info/METADATA
graphqt-0.2.dist-info/RECORD
graphqt-0.2.dist-info/WHEEL
graphqt-0.2.dist-info/metadata.json
graphqt-0.2.dist-info/top_level.txt
