Metadata-Version: 2.0
Name: graphqt
Version: 0.2
Summary: Create Graph DataStructure
Home-page: https://github.com/ToughX-devs/graphqt-python
Author: Amit Singh Sansoya
Author-email: tusharamit@yahoo.com
License: MIT
Platform: UNKNOWN
Classifier: Programming Language :: Python :: 3
Classifier: Operating System :: OS Independent
